LeetcodeWrapper/__init__.py
LeetcodeWrapper/api.py
LeetcodeWrapper/exceptions.py
LeetcodeWrapper/utils.py
tests/__init__.py
tests/test_api.py
leetcode_api_wrapper-1.1.2.dist-info/LICENSE
leetcode_api_wrapper-1.1.2.dist-info/METADATA
leetcode_api_wrapper-1.1.2.dist-info/WHEEL
leetcode_api_wrapper-1.1.2.dist-info/top_level.txt
leetcode_api_wrapper-1.1.2.dist-info/RECORD
