Metadata-Version: 2.1
Name: leetcode-api-wrapper
Version: 1.1.2
Summary: Python wrapper for Alfa LeetCode API
Home-page: https://github.com/harbringe/pyleetcode
Author: Aaditya Mehetre
Author-email: aadityamehetre@icloud.com
Classifier: Programming Language :: Python :: 3
Classifier: License :: OSI Approved :: MIT License
Classifier: Operating System :: OS Independent
Requires-Python: >=3.7
License-File: LICENSE
Requires-Dist: requests>=2.25.1
